pyelong
