Metadata-Version: 1.0
Name: pyelong
Version: 0.5.2
Summary: Python SDK for Elong (http://elong.com/) rest APIs.
Home-page: https://github.com/DeanThompson/pyelong
Author: Yangliang Li
Author-email: yanglianglee@gmail.com
License: MIT
Platform: UNKNOWN
